inec/__init__.py
inec/core.py
inec-0.1.2.dist-info/licenses/LICENSE
inec-0.1.2.dist-info/METADATA
inec-0.1.2.dist-info/WHEEL
inec-0.1.2.dist-info/top_level.txt
inec-0.1.2.dist-info/RECORD
