Metadata-Version: 2.4
Name: inec
Version: 0.1.2
Summary: Method for accessing INEC data directly from Python
Author-email: Marco Piedra <apiedram@gmail.com>
License-File: LICENSE
Requires-Dist: requests
Requires-Dist: pandas
Requires-Dist: beautifulsoup4
Requires-Dist: certifi
Requires-Dist: pyreadstat
Requires-Dist: openpyxl
Dynamic: license-file
